aamutils/__init__.py
aamutils/__main__.py
aamutils/aam_expand.py
aamutils/mapping.py
aamutils/utils.py
aamutils/algorithm/__init__.py
aamutils/algorithm/aaming.py
aamutils/algorithm/ilp.py
aamutils/cmd/__init__.py
aamutils/cmd/expanding.py
aamutils-0.0.10.dist-info/METADATA
aamutils-0.0.10.dist-info/WHEEL
aamutils-0.0.10.dist-info/licenses/LICENSE
aamutils-0.0.10.dist-info/RECORD
