Metadata-Version: 2.4
Name: aamutils
Version: 0.0.10
Summary: Collection of atom-atom-mapping utility functions.
Project-URL: homepage, https://github.com/klausweinbauer/AAMUtils
Project-URL: source, https://github.com/klausweinbauer/AAMUtils
Project-URL: issues, https://github.com/klausweinbauer/AAMUtils/issues
Author-email: Klaus Weinbauer <klaus@bioinf.uni-leipzig.de>
License-File: LICENSE
Classifier: License :: OSI Approved :: MIT License
Classifier: Operating System :: OS Independent
Classifier: Programming Language :: Python :: 3
Requires-Python: >=3.11
Requires-Dist: fgutils<0.1.0,>=0.0.17
Requires-Dist: networkx>=3.4.2
Requires-Dist: pillow==10.3.0
Requires-Dist: pulp==2.8.0
Requires-Dist: rdkit>=2024.3.3
Requires-Dist: scipy>=1.14.0
